miracle/__init__.py
miracle/miracle.py
miracle0927-1.0.0.dist-info/LICENSE
miracle0927-1.0.0.dist-info/METADATA
miracle0927-1.0.0.dist-info/WHEEL
miracle0927-1.0.0.dist-info/top_level.txt
miracle0927-1.0.0.dist-info/RECORD
